hyperframe/__init__.py
hyperframe/exceptions.py
hyperframe/flags.py
hyperframe/frame.py
hyperframe-5.0.0.dist-info/DESCRIPTION.rst
hyperframe-5.0.0.dist-info/METADATA
hyperframe-5.0.0.dist-info/RECORD
hyperframe-5.0.0.dist-info/WHEEL
hyperframe-5.0.0.dist-info/metadata.json
hyperframe-5.0.0.dist-info/top_level.txt
